tilecloud/__init__.py
tilecloud/filter/__init__.py
tilecloud/filter/benchmark.py
tilecloud/filter/consistenthash.py
tilecloud/filter/contenttype.py
tilecloud/filter/error.py
tilecloud/filter/gzip_.py
tilecloud/filter/image.py
tilecloud/filter/inboundingpyramid.py
tilecloud/filter/logger.py
tilecloud/filter/optipng.py
tilecloud/filter/rate.py
tilecloud/grid/__init__.py
tilecloud/grid/free.py
tilecloud/grid/google.py
tilecloud/grid/quad.py
tilecloud/layout/__init__.py
tilecloud/layout/i3d.py
tilecloud/layout/osm.py
tilecloud/layout/re_.py
tilecloud/layout/template.py
tilecloud/layout/tilecache.py
tilecloud/layout/wms.py
tilecloud/layout/wmts.py
tilecloud/layout/wrapped.py
tilecloud/lib/PIL_.py
tilecloud/lib/__init__.py
tilecloud/lib/memcached.py
tilecloud/lib/sqlite3_.py
tilecloud/lib/wmts.py
tilecloud/lib/wmts_get_capabilities_template.py
tilecloud/py.typed
tilecloud/scripts/__init__.py
tilecloud/scripts/tc_copy.py
tilecloud/scripts/tc_delete.py
tilecloud/scripts/tc_info.py
tilecloud/scripts/tc_mask.py
tilecloud/scripts/tc_mbtiles_create.py
tilecloud/scripts/tc_mbtiles_info.py
tilecloud/scripts/tc_refine_bounds.py
tilecloud/scripts/tc_viewer.py
tilecloud/store/__init__.py
tilecloud/store/azure_storage_blob.py
tilecloud/store/boundingpyramid.py
tilecloud/store/bsddb.py
tilecloud/store/debug.py
tilecloud/store/dict.py
tilecloud/store/filesystem.py
tilecloud/store/filtered.py
tilecloud/store/findfirst.py
tilecloud/store/log.py
tilecloud/store/mapnik_.py
tilecloud/store/mask.py
tilecloud/store/mbtiles.py
tilecloud/store/memcached.py
tilecloud/store/metatile.py
tilecloud/store/null.py
tilecloud/store/queue.py
tilecloud/store/redis.py
tilecloud/store/renderingtheworld.py
tilecloud/store/s3.py
tilecloud/store/searchup.py
tilecloud/store/sqs.py
tilecloud/store/tilecache.py
tilecloud/store/tilejson.py
tilecloud/store/url.py
tilecloud/store/wmts.py
tilecloud/store/zip.py
tilecloud/tests/__init__.py
tilecloud/tests/test_boundingpyramid.py
tilecloud/tests/test_bounds.py
tilecloud-1.13.5.dist-info/LICENSE
tilecloud-1.13.5.dist-info/METADATA
tilecloud-1.13.5.dist-info/WHEEL
tilecloud-1.13.5.dist-info/entry_points.txt
tilecloud-1.13.5.dist-info/RECORD
