Metadata-Version: 2.3
Name: tilecloud
Version: 1.13.5
Summary: Tools for managing tiles
License: BSD-2-Clause
Keywords: gis,tilecloud
Author: Camptocamp
Author-email: info@camptocamp.com
Requires-Python: >=3.10
Classifier: Development Status :: 6 - Mature
Classifier: Environment :: Console
Classifier: Intended Audience :: Developers
Classifier: License :: OSI Approved :: BSD License
Classifier: Programming Language :: Python
Classifier: Programming Language :: Python :: 3
Classifier: Programming Language :: Python :: 3.10
Classifier: Programming Language :: Python :: 3.11
Classifier: Programming Language :: Python :: 3.12
Classifier: Programming Language :: Python :: 3.13
Classifier: Topic :: Scientific/Engineering :: GIS
Classifier: Typing :: Typed
Provides-Extra: all
Provides-Extra: aws
Provides-Extra: azure
Provides-Extra: prometheus
Provides-Extra: redis
Provides-Extra: wsgi
Requires-Dist: Pillow
Requires-Dist: azure-identity ; extra == "azure" or extra == "all"
Requires-Dist: azure-storage-blob ; extra == "azure" or extra == "all"
Requires-Dist: boto3 ; extra == "aws" or extra == "all"
Requires-Dist: bottle
Requires-Dist: cryptography
Requires-Dist: prometheus_client ; extra == "prometheus" or extra == "all"
Requires-Dist: pyproj
Requires-Dist: pyramid ; extra == "wsgi" or extra == "all"
Requires-Dist: redis ; extra == "redis" or extra == "all"
Requires-Dist: requests
Project-URL: Repository, https://github.com/camptocamp/tilecloud
